Metadata-Version: 1.0
Name: pysui-irors-TEST
Version: 3.0
Summary: pysui_remake
Home-page: UNKNOWN
Author: UNKNOWN
Author-email: rskafh@gmail.com
License: UNKNOWN
Platform: UNKNOWN
